odoo/addons/stock_production_lot_active/README.rst
odoo/addons/stock_production_lot_active/__init__.py
odoo/addons/stock_production_lot_active/__manifest__.py
odoo/addons/stock_production_lot_active/i18n/stock_production_lot_active.pot
odoo/addons/stock_production_lot_active/models/__init__.py
odoo/addons/stock_production_lot_active/models/stock_production_lot.py
odoo/addons/stock_production_lot_active/readme/CONTRIBUTORS.rst
odoo/addons/stock_production_lot_active/readme/DESCRIPTION.rst
odoo/addons/stock_production_lot_active/static/description/icon.png
odoo/addons/stock_production_lot_active/static/description/index.html
odoo/addons/stock_production_lot_active/views/stock_production_lot.xml
odoo13_addon_stock_production_lot_active-13.0.1.0.1.dev4.dist-info/METADATA
odoo13_addon_stock_production_lot_active-13.0.1.0.1.dev4.dist-info/WHEEL
odoo13_addon_stock_production_lot_active-13.0.1.0.1.dev4.dist-info/top_level.txt
odoo13_addon_stock_production_lot_active-13.0.1.0.1.dev4.dist-info/RECORD
